pathio/__init__.py
pathio/iopaths.py
pathio/mk_rm_dir.py
pathio/prepare_paths.py
pathio-0.1.0.dist-info/LICENSE
pathio-0.1.0.dist-info/METADATA
pathio-0.1.0.dist-info/WHEEL
pathio-0.1.0.dist-info/RECORD
