Metadata-Version: 2.3
Name: pathio
Version: 0.1.0
Summary: Input and output path checks. Simplifies handling of file/directory paths in scripts.
License: MIT
Keywords: path,checks,scripts
Author: Ludvig
Author-email: <mail@ludvigolsen.dk>
Requires-Python: >=3.8,<4.0
Classifier: License :: OSI Approved :: MIT License
Classifier: Programming Language :: Python :: 3
Classifier: Programming Language :: Python :: 3.8
Classifier: Programming Language :: Python :: 3.9
Classifier: Programming Language :: Python :: 3.10
Classifier: Programming Language :: Python :: 3.11
Classifier: Programming Language :: Python :: 3.12
Classifier: Programming Language :: Python :: 3.13
Project-URL: Changelog, https://github.com/ludvigolsen/pathio/blob/main/CHANGELOG.md
Project-URL: Issues, https://github.com/ludvigolsen/pathio/issues
Project-URL: Repository, https://github.com/ludvigolsen/pathio
